binni2/__init__.py
binni2/__version__.py
binni2/_internal_utils.py
binni2/adapters.py
binni2/api.py
binni2/auth.py
binni2/certs.py
binni2/compat.py
binni2/cookies.py
binni2/exceptions.py
binni2/help.py
binni2/hooks.py
binni2/models.py
binni2/packages.py
binni2/sessions.py
binni2/status_codes.py
binni2/structures.py
binni2/utils.py
binni2-0.0.1.dist-info/LICENSE
binni2-0.0.1.dist-info/METADATA
binni2-0.0.1.dist-info/WHEEL
binni2-0.0.1.dist-info/top_level.txt
binni2-0.0.1.dist-info/RECORD
